miyadaiku/themes/tether/__init__.py
miyadaiku/themes/tether/__version__.py
miyadaiku/themes/tether/config.yml
miyadaiku/themes/tether/externals/js/tether.js
miyadaiku/themes/tether/externals/js/tether.min.js
miyadaiku/themes/tether/templates/macros.html
miyadaiku.themes.tether-0.0.8.dist-info/METADATA
miyadaiku.themes.tether-0.0.8.dist-info/WHEEL
miyadaiku.themes.tether-0.0.8.dist-info/top_level.txt
miyadaiku.themes.tether-0.0.8.dist-info/RECORD
