Metadata-Version: 2.1
Name: miyadaiku.themes.tether
Version: 0.0.8
Summary: Tether files for miyadaiku static site generator
Home-page: https://github.com/miyadaiku/miyadaiku-themes-tether
Author: Atsuo Ishimoto
Author-email: UNKNOWN
License: MIT
Project-URL: Miyadaiku, https://miyadaiku.github.io/
Platform: UNKNOWN
Classifier: Programming Language :: Python :: 3
Classifier: Programming Language :: Python :: 3.6
Classifier: Programming Language :: Python :: 3.7
Requires-Dist: miyadaiku
